Metadata-Version: 2.4
Name: il-supermarket-scraper
Version: 0.6.3
Summary: python package that implement a scraping for israeli supermarket data
Home-page: https://github.com/OpenIsraeliSupermarkets/israeli-supermarket-scarpers
Author: Sefi Erlich
Author-email: erlichsefi@gmail.com
License: MIT
Keywords: israel,israeli,scraper,supermarket
Classifier: Development Status :: 3 - Alpha
Classifier: Intended Audience :: Developers
Classifier: Topic :: Software Development :: Build Tools
Classifier: License :: OSI Approved :: MIT License
Classifier: Programming Language :: Python :: 3
Classifier: Programming Language :: Python :: 3.4
Classifier: Programming Language :: Python :: 3.5
Classifier: Programming Language :: Python :: 3.6
License-File: LICENSE.txt
Requires-Dist: retry==0.9.2
Requires-Dist: mock==4.0.3
Requires-Dist: requests==2.32.2
Requires-Dist: lxml==5.2.1
Requires-Dist: beautifulsoup4==4.10.0
Requires-Dist: pymongo==4.6.3
Requires-Dist: dnspython==2.6.1
Requires-Dist: pytz==2022.4
Requires-Dist: holidays==0.45
Requires-Dist: cachetools==5.2.0
Requires-Dist: pytest-playwright==0.7.0
Provides-Extra: test
Requires-Dist: pytest; extra == "test"
Requires-Dist: pytest-xdist; extra == "test"
Dynamic: author
Dynamic: author-email
Dynamic: classifier
Dynamic: description
Dynamic: description-content-type
Dynamic: home-page
Dynamic: keywords
Dynamic: license
Dynamic: license-file
Dynamic: provides-extra
Dynamic: requires-dist
Dynamic: summary
